svghelper/__init__.py
svghelper/main.py
svghelper-0.0.6.dist-info/LICENSE
svghelper-0.0.6.dist-info/METADATA
svghelper-0.0.6.dist-info/WHEEL
svghelper-0.0.6.dist-info/top_level.txt
svghelper-0.0.6.dist-info/RECORD
