Metadata-Version: 2.1
Name: svghelper
Version: 0.0.6
Summary: Python SVG helper. set svg color, etc.
Home-page: https://github.com/yjg30737/svghelper.git
Author: Jung Gyu Yoon
Author-email: yjg30737@gmail.com
License: MIT
Platform: UNKNOWN
License-File: LICENSE
Requires-Dist: colorgetter (>=0.0.1)
